pissy/__init__.py
pissy/app.py
pissy/config.py
pissy/const.py
pissy/core.py
pissy/db_register.py
pissy/dbms_core.py
pissy/dbms_models.py
pissy/dialect.py
pissy/executions.py
pissy/kafka_core.py
pissy/kafka_register.py
pissy/logger.conf
pissy/sched.py
pissy/task.py
pissy/task_config_loader.py
pissy/task_config_validator.py
pissy/task_graph_helper.py
pissy/task_loader.py
pissy/commands/__init__.py
pissy/commands/demo_config_command.py
pissy/commands/start_task_command.py
pissy/extensions/__init__.py
pissy/extensions/dbms/__init__.py
pissy/extensions/dbms/db_register.py
pissy/extensions/dbms/dbms_core.py
pissy/extensions/dbms/dbms_models.py
pissy/extensions/dbms/dialect.py
pissy/extensions/kafka/__init__.py
pissy/extensions/kafka/kafka_core.py
pissy/extensions/kafka/kafka_register.py
pissy-0.0.6.dist-info/LICENSE
pissy-0.0.6.dist-info/METADATA
pissy-0.0.6.dist-info/WHEEL
pissy-0.0.6.dist-info/entry_points.txt
pissy-0.0.6.dist-info/top_level.txt
pissy-0.0.6.dist-info/RECORD
