Metadata-Version: 2.1
Name: pissy
Version: 0.0.6
License-File: LICENSE
Requires-Dist: sqlalchemy ==2.0.36
Requires-Dist: cx-oracle ==8.3.0
Requires-Dist: pymysql ==1.1.1
Requires-Dist: python-box ==7.2.0
Requires-Dist: jsonschema ==4.23.0
Requires-Dist: kafka-python-ng
